portfawn/__init__.py
portfawn/backtest/__init__.py
portfawn/backtest/backtest.py
portfawn/models/__init__.py
portfawn/models/optimization.py
portfawn/models/risk.py
portfawn/models/utils.py
portfawn/plot/__init__.py
portfawn/plot/multi_portfolio.py
portfawn/plot/plot.py
portfawn/plot/portfolio.py
portfawn/portfolio/__init__.py
portfawn/portfolio/base.py
portfawn/portfolio/equally_weighted.py
portfawn/portfolio/mean_variance.py
portfawn/portfolio/random.py
PortFawn-0.0.1.dist-info/LICENSE
PortFawn-0.0.1.dist-info/METADATA
PortFawn-0.0.1.dist-info/WHEEL
PortFawn-0.0.1.dist-info/top_level.txt
PortFawn-0.0.1.dist-info/RECORD
