Metadata-Version: 2.1
Name: PortFawn
Version: 0.0.1
Summary: Portfolio Optimization
Home-page: https://github.com/mkareshk/portfawn
Author: Moein Kareshk
Author-email: mkareshk@outlook.com
Classifier: Programming Language :: Python :: 3
Classifier: License :: OSI Approved :: MIT License
Classifier: Operating System :: OS Independent
Requires-Python: >=3.10
License-File: LICENSE
Requires-Dist: scikit-learn
Requires-Dist: seaborn
Requires-Dist: dafin>=0.0.3
Provides-Extra: quantum
Requires-Dist: dwave-system>=1.25.0; extra == "quantum"
Requires-Dist: dwave-neal>=0.6.0; extra == "quantum"
Provides-Extra: dev
Requires-Dist: pre-commit; extra == "dev"
Requires-Dist: pytest; extra == "dev"
Requires-Dist: pytest-runner; extra == "dev"
Requires-Dist: pytest-cov; extra == "dev"
Requires-Dist: parameterized; extra == "dev"
Requires-Dist: pylint; extra == "dev"
